<?xml version="1.0" encoding="UTF-8"?>
<ContextState>
<org.eclipse.mylyn.context.ui.editors>
<MonitoredWindowOpenEditors class="org.eclipse.ui.internal.WorkbenchWindow" isActive="true" isLaunching="true" number="0">
<editor id="org.eclipse.php.editor">
<input factoryID="org.eclipse.ui.part.FileEditorInputFactory" path="/Cake_NR5/app/Controller/TokensController.php"/>
<editorState selectionHorizontalPixel="0" selectionLength="0" selectionOffset="424" selectionTopPixel="130"/>
</editor>
<editor id="org.eclipse.php.editor">
<input factoryID="org.eclipse.ui.part.FileEditorInputFactory" path="/Cake_NR5/app/Controller/HistorysController.php"/>
<editorState selectionHorizontalPixel="0" selectionLength="0" selectionOffset="19836" selectionTopPixel="21627"/>
</editor>
<editor id="org.eclipse.php.editor">
<input factoryID="org.eclipse.ui.part.FileEditorInputFactory" path="/Cake_NR5/app/View/Historys/index.ctp"/>
<editorState selectionHorizontalPixel="0" selectionLength="0" selectionOffset="379" selectionTopPixel="0"/>
</editor>
<editor id="org.eclipse.php.editor">
<input factoryID="org.eclipse.ui.part.FileEditorInputFactory" path="/Cake_NR5/app/View/Elements/tokens/index_t_headers.ctp"/>
<editorState selectionHorizontalPixel="0" selectionLength="0" selectionOffset="723" selectionTopPixel="832"/>
</editor>
<editor id="org.eclipse.php.editor">
<input factoryID="org.eclipse.ui.part.FileEditorInputFactory" path="/Cake_NR5/app/View/Elements/tokens/_index_pagination.ctp"/>
<editorState selectionHorizontalPixel="0" selectionLength="0" selectionOffset="468" selectionTopPixel="350"/>
</editor>
<editor id="org.eclipse.php.editor">
<input factoryID="org.eclipse.ui.part.FileEditorInputFactory" path="/Cake_NR5/app/Lib/utils/CONS.php"/>
<editorState selectionHorizontalPixel="0" selectionLength="0" selectionOffset="470" selectionTopPixel="0"/>
</editor>
</MonitoredWindowOpenEditors>
</org.eclipse.mylyn.context.ui.editors>
</ContextState>