<?xml version="1.0" encoding="UTF-8"?>
<ContextState>
<org.eclipse.mylyn.context.ui.editors>
<MonitoredWindowOpenEditors class="org.eclipse.ui.internal.WorkbenchWindow" isActive="true" isLaunching="true" number="0">
<editor id="org.eclipse.php.editor">
<input factoryID="org.eclipse.ui.part.FileEditorInputFactory" path="/CR6_cake/app/View/Texts/view.ctp"/>
<editorState selectionHorizontalPixel="0" selectionLength="0" selectionOffset="560" selectionTopPixel="226"/>
</editor>
<editor id="org.eclipse.php.editor">
<input factoryID="org.eclipse.ui.part.FileEditorInputFactory" path="/CR6_cake/app/View/Elements/texts/view/_view_title_text.ctp"/>
<editorState selectionHorizontalPixel="0" selectionLength="0" selectionOffset="137" selectionTopPixel="0"/>
</editor>
<editor id="org.eclipse.php.editor">
<input factoryID="org.eclipse.ui.part.FileEditorInputFactory" path="/CR6_cake/app/Controller/TextsController.php"/>
<editorState selectionHorizontalPixel="0" selectionLength="35" selectionOffset="9795" selectionTopPixel="9909"/>
</editor>
</MonitoredWindowOpenEditors>
</org.eclipse.mylyn.context.ui.editors>
</ContextState>